GetElevation/GetElevation.py
GetElevation/__init__.py
GetElevation-0.1.dist-info/License
GetElevation-0.1.dist-info/METADATA
GetElevation-0.1.dist-info/WHEEL
GetElevation-0.1.dist-info/top_level.txt
GetElevation-0.1.dist-info/RECORD
