Metadata-Version: 2.1
Name: GetElevation
Version: 0.1
Summary: 这是一个批量/单次查询经高程的模块
Author: 吴镇江
Author-email: 852356187@qq.com
Classifier: Programming Language :: Python :: 3
Classifier: License :: OSI Approved :: MIT License
Classifier: Operating System :: OS Independent
Requires-Python: >=3
License-File: License
Requires-Dist: requests
Requires-Dist: pandas
